playsh/__init__.py
playsh/error.py
playsh/input.py
playsh/playsh.py
playsh/store.py
playsh/timer.py
playsh/graphics/__init__.py
playsh/graphics/geometry.py
playsh/graphics/renderer.py
playsh/graphics/shader.py
playsh/graphics/texture.py
playsh-0.0.2.dist-info/LICENSE
playsh-0.0.2.dist-info/METADATA
playsh-0.0.2.dist-info/WHEEL
playsh-0.0.2.dist-info/top_level.txt
playsh-0.0.2.dist-info/RECORD
