Metadata-Version: 2.1
Name: playsh
Version: 0.0.2
Summary: A playground for OpenGL fragment shader
Home-page: https://github.com/panmar/playsh
Author: Marcin Panasiuk
Author-email: panasiuk.marcin@gmail.com
License: UNKNOWN
Platform: UNKNOWN
Classifier: Programming Language :: Python :: 3
Classifier: Programming Language :: Python :: 3.9
Classifier: Operating System :: OS Independent
License-File: LICENSE
Requires-Dist: injector
Requires-Dist: glfw
Requires-Dist: PyOpenGL
Requires-Dist: PyGLM
Requires-Dist: numpy
Requires-Dist: pillow
Provides-Extra: dev
Requires-Dist: black ; extra == 'dev'
Requires-Dist: mypy ; extra == 'dev'
